xlsxgrep/__init__.py
xlsxgrep/xlsxgrep.py
xlsxgrep-0.0.30.dist-info/licenses/LICENSE
xlsxgrep-0.0.30.dist-info/METADATA
xlsxgrep-0.0.30.dist-info/WHEEL
xlsxgrep-0.0.30.dist-info/entry_points.txt
xlsxgrep-0.0.30.dist-info/top_level.txt
xlsxgrep-0.0.30.dist-info/RECORD
