Metadata-Version: 2.4
Name: xlsxgrep
Version: 0.0.30
Summary: CLI tool to search text in XLSX, XLS, XLSM, CSV, TSV and ODS files. It works similarly to Unix\GNU Linux grep.
Home-page: https://github.com/zazuum/xlsxgrep
Author: Ivan Cvitic
Author-email: cviticivan@gmail.com
License: MIT
Classifier: Environment :: Console
Classifier: License :: OSI Approved :: MIT License
Classifier: Intended Audience :: Developers
Classifier: Intended Audience :: Education
Classifier: Intended Audience :: System Administrators
Classifier: Intended Audience :: Science/Research
Classifier: Intended Audience :: End Users/Desktop
Classifier: Operating System :: OS Independent
Classifier: Programming Language :: Python :: 3
Classifier: Programming Language :: Python :: 3.7
Classifier: Programming Language :: Python :: 3.8
Classifier: Programming Language :: Python :: 3.9
Classifier: Programming Language :: Python :: 3.10
Classifier: Programming Language :: Python :: 3.11
Classifier: Programming Language :: Python :: 3.12
Classifier: Programming Language :: Python :: 3.13
Classifier: Topic :: Scientific/Engineering
Classifier: Topic :: Scientific/Engineering :: Information Analysis
Classifier: Topic :: Scientific/Engineering :: Bio-Informatics
Classifier: Topic :: Office/Business
Classifier: Topic :: Office/Business :: Financial
Classifier: Topic :: Office/Business :: Financial :: Spreadsheet
Classifier: Topic :: Utilities
License-File: LICENSE
Requires-Dist: pyexcel
Requires-Dist: pyexcel-xls
Requires-Dist: pyexcel-xlsx
Requires-Dist: pyexcel-odsr
Dynamic: license-file
